sentinex/__init__.py
sentinex/module.py
sentinex/pytree.py
sentinex/version.py
sentinex/core/__init__.py
sentinex/core/config.py
sentinex/core/custom_ops.py
sentinex/modelzoo/__init__.py
sentinex/modelzoo/perceptron.py
sentinex/nn/__init__.py
sentinex/train_utils/__init__.py
sentinex/train_utils/training_loop.py
sentinex-0.0.1.dist-info/METADATA
sentinex-0.0.1.dist-info/WHEEL
sentinex-0.0.1.dist-info/top_level.txt
sentinex-0.0.1.dist-info/RECORD
